batoms/__init__.py
batoms/attribute.py
batoms/batoms.py
batoms/boundary.py
batoms/bselect.py
batoms/bspecies.py
batoms/build.py
batoms/cell.py
batoms/console.py
batoms/logger.py
batoms/metaball.py
batoms/neighborlist.py
batoms/pdbparser.py
batoms/preferences.py
batoms/slicebatoms.py
batoms/volumetric_data.py
batoms/asset/__init__.py
batoms/asset/asset.py
batoms/asset/ops.py
batoms/asset/utils.py
batoms/asset/libraries/__init__.py
batoms/asset/libraries/modifiers.blend
batoms/base/__init__.py
batoms/base/collection.py
batoms/base/object.py
batoms/bio/__init__.py
batoms/bio/bio.py
batoms/bond/__init__.py
batoms/bond/bond.py
batoms/bond/bpy_data.py
batoms/bond/gui.py
batoms/bond/gui_slicebonds.py
batoms/bond/ops.py
batoms/bond/search_bond.py
batoms/bond/setting.py
batoms/bond/slicebonds.py
batoms/data/__init__.py
batoms/data/source_data.py
batoms/database/__init__.py
batoms/database/mp.py
batoms/database/pubchem.py
batoms/database/pymatgen.py
batoms/database/rscb.py
batoms/draw/__init__.py
batoms/draw/draw_screen.py
batoms/gui/__init__.py
batoms/gui/gui_batoms.py
batoms/gui/gui_cell.py
batoms/gui/gui_io.py
batoms/gui/gui_plane.py
batoms/gui/gui_render.py
batoms/gui/gui_slicebatoms.py
batoms/gui/gui_toolbar.py
batoms/gui/gui_volumetric_data.py
batoms/gui/ui_list_species.py
batoms/gui/utils.py
batoms/gui/view3d_mt_batoms_add.py
batoms/gui/view3d_mt_edit_mesh_context_menu.py
batoms/gui/view3d_mt_object_context_menu.py
batoms/install/__init__.py
batoms/install/pip_dependencies.py
batoms/install/update.py
batoms/internal_data/__init__.py
batoms/internal_data/bpy_data.py
batoms/material/__init__.py
batoms/ops/__init__.py
batoms/ops/add_nanoparticle.py
batoms/ops/add_nanoribbon.py
batoms/ops/add_nanotube.py
batoms/ops/add_object.py
batoms/ops/add_surface.py
batoms/ops/base.py
batoms/ops/label.py
batoms/ops/manual_mapping.py
batoms/ops/measure.py
batoms/ops/molecule_edit_atom.py
batoms/ops/molecule_edit_bond.py
batoms/ops/ops_batoms.py
batoms/ops/ops_io.py
batoms-2.4.0.1.dist-info/LICENSE
batoms-2.4.0.1.dist-info/METADATA
batoms-2.4.0.1.dist-info/WHEEL
batoms-2.4.0.1.dist-info/top_level.txt
batoms-2.4.0.1.dist-info/RECORD
