Metadata-Version: 2.1
Name: batoms
Version: 2.4.0.1
Summary: A Python package for creating, editing and rendering atoms and molecules structures using Blender.
Home-page: https://github.com/beautiful-atoms/beautiful-atoms
Author: Beautiful Atoms Team
Author-email: xing.wang@gmail.com
License: GPL
Classifier: License :: OSI Approved :: GNU General Public License v3 (GPLv3)
Classifier: Programming Language :: Python :: 3
Requires-Python: >=3.10, <4
License-File: LICENSE
Requires-Dist: bpy
Requires-Dist: ase
